trame/__init__.py
trame/modules/__init__.py
trame/modules/mesh_streamer.py
trame/widgets/__init__.py
trame/widgets/mesh_streamer.py
trame_mesh_streamer/__init__.py
trame_mesh_streamer/protocol.py
trame_mesh_streamer/module/__init__.py
trame_mesh_streamer/module/serve/demo.html
trame_mesh_streamer/module/serve/vue-trame_mesh_streamer.common.js
trame_mesh_streamer/module/serve/vue-trame_mesh_streamer.common.js.map
trame_mesh_streamer/module/serve/vue-trame_mesh_streamer.css
trame_mesh_streamer/module/serve/vue-trame_mesh_streamer.umd.js
trame_mesh_streamer/module/serve/vue-trame_mesh_streamer.umd.js.map
trame_mesh_streamer/module/serve/vue-trame_mesh_streamer.umd.min.js
trame_mesh_streamer/module/serve/vue-trame_mesh_streamer.umd.min.js.map
trame_mesh_streamer/widgets/__init__.py
trame_mesh_streamer/widgets/mesh_streamer.py
trame_mesh_streamer-0.1.0.dist-info/LICENSE
trame_mesh_streamer-0.1.0.dist-info/METADATA
trame_mesh_streamer-0.1.0.dist-info/WHEEL
trame_mesh_streamer-0.1.0.dist-info/top_level.txt
trame_mesh_streamer-0.1.0.dist-info/RECORD
