Metadata-Version: 2.1
Name: trame-mesh-streamer
Version: 0.1.0
Summary: Client/Server library for progressive delivery of meshes
Home-page: UNKNOWN
Author: Kitware Inc.
License: Apache Software License
Keywords: Python,Interactive,Web,Application,Framework
Platform: UNKNOWN
Classifier: Development Status :: 4 - Beta
Classifier: Environment :: Web Environment
Classifier: License :: OSI Approved :: Apache Software License
Classifier: Natural Language :: English
Classifier: Operating System :: OS Independent
Classifier: Programming Language :: Python :: 3 :: Only
Classifier: Programming Language :: JavaScript
Classifier: Topic :: Software Development :: Libraries :: Application Frameworks
Classifier: Topic :: Software Development :: Libraries :: Python Modules
License-File: LICENSE
Requires-Dist: trame-client
